<?xml version="1.0" encoding="UTF-8" standalone="no"?>
<compiereTrl baseLanguage="en_US" language="es_ES" table="AD_ELEMENT" version="">
  <row id="188A891302344C5D8C239307813A10AF" trl="Y">
    <value column="Name" isTrl="Y" original="em_smscp_state">Estado</value>
    <value column="PrintName" isTrl="Y" original="em_smscp_state">Estado</value>
    <value column="Description" isTrl="N" original=""/>
    <value column="Help" isTrl="N" original=""/>
    <value column="PO_Description" isTrl="N" original=""/>
    <value column="PO_Help" isTrl="N" original=""/>
    <value column="PO_Name" isTrl="N" original=""/>
    <value column="PO_PrintName" isTrl="N" original=""/>
  </row>
  <row id="19BB734D8CE04ABCB2D5A1AE2B5CD8B9" trl="Y">
    <value column="Name" isTrl="Y" original="em_smscp_enddate">Fecha fin</value>
    <value column="PrintName" isTrl="Y" original="em_smscp_enddate">Fecha fin</value>
    <value column="Description" isTrl="N" original=""/>
    <value column="Help" isTrl="N" original=""/>
    <value column="PO_Description" isTrl="N" original=""/>
    <value column="PO_Help" isTrl="N" original=""/>
    <value column="PO_Name" isTrl="N" original=""/>
    <value column="PO_PrintName" isTrl="N" original=""/>
  </row>
  <row id="CCED2630725E430DA927C81F6987B5C3" trl="Y">
    <value column="Name" isTrl="Y" original="em_smscp_startdate">Fecha inicio</value>
    <value column="PrintName" isTrl="Y" original="em_smscp_startdate">Fecha inicio</value>
    <value column="Description" isTrl="N" original=""/>
    <value column="Help" isTrl="N" original=""/>
    <value column="PO_Description" isTrl="N" original=""/>
    <value column="PO_Help" isTrl="N" original=""/>
    <value column="PO_Name" isTrl="N" original=""/>
    <value column="PO_PrintName" isTrl="N" original=""/>
  </row>
</compiereTrl>
